sentiment_analysis/__init__.py
sentiment_analysis/sentiment.py
sentiment_analysis/lexicon/expressive-type.csv
sentiment_analysis/lexicon/intensity.csv
sentiment_analysis/lexicon/nested-order.csv
sentiment_analysis/lexicon/polarity.csv
sentiment_analysis/lexicon/subjectivity-polarity.csv
sentiment_analysis/lexicon/subjectivity-type.csv
sentiment_analysis_ko-0.0.1a0.dist-info/LICENSE
sentiment_analysis_ko-0.0.1a0.dist-info/METADATA
sentiment_analysis_ko-0.0.1a0.dist-info/WHEEL
sentiment_analysis_ko-0.0.1a0.dist-info/top_level.txt
sentiment_analysis_ko-0.0.1a0.dist-info/RECORD
